{"AMER":{"AMER 437":{"name":"American Film in Context","sections":{"1":{"instructor":"Muammer Şanlı","schedule":{"7":"G-110","8":"G-110","9":"G-110","14":"G-110","15":"G-110","16":"G-110"}}}}},"BF":{"BF 365":{"name":"Elements of Money and Banking","sections":{"1":{"instructor":"Nazmi Demir","schedule":{"8":"LD-4","9":"LD-4","15":"LD-4","16":"LD-4","22":"LD-4","23":"LD-4"}}}},"BF 405":{"name":"Intercultural Business Communication","sections":{"1":{"instructor":"Elizabeth Saatçi","schedule":{"0":"LA-101","2":"LA-101","7":"LA-101","9":"LA-101","14":"LA-101","16":"LA-101","42":"LA-101","44":"LA-101","49":"LA-101","51":"LA-101","56":"LA-101","58":"LA-101"}}}},"BF 461":{"name":"Corporate Finance","sections":{"1":{"instructor":"Mustafa Egeli","schedule":{"3":"LA-103","10":"LA-103","12":"N/A","17":"LA-103","19":"N/A","26":"N/A"}}}},"BF 462":{"name":"Investments","sections":{"1":{"instructor":"Sedat Çilingir","schedule":{"2":"LA-103","9":"LA-103","16":"LA-103","35":"LA-103","42":"LA-103","49":"LA-103"}}}},"BF 464":{"name":"International Finance","sections":{"1":{"instructor":"Sedat Çilingir","schedule":{"7":"LB-101","14":"LB-101","21":"LB-101","38":"LB-101","45":"LB-101","52":"LB-101"}}}},"BF 476":{"name":"Computerized Financial Analysis","sections":{"1":{"instructor":"Nazmi Demir","schedule":{}}}}},"BIM":{"BIM 375":{"name":"Public Relations","sections":{"1":{"instructor":"Elif Sibel Özdilek","schedule":{}}}},"BIM 390":{"name":"Summer Training","sections":{"1":{"instructor":"Staff","schedule":{}}}},"BIM 405":{"name":"Organizational Behaviour","sections":{"1":{"instructor":"Zeynep İşcan","schedule":{}}}},"BIM 409":{"name":"Studies in Finance","sections":{"1":{"instructor":"Anthony Burnett Evans","schedule":{}}}}},"CS":{"CS 102":{"name":"Algorithms and Programming II","sections":{"1":{"instructor":"Uğur Güdükbay","schedule":{"36":"B-303","39":"B-303","42":"EB-201","43":"B-303","44":"EB-201","46":"B-303","49":"EB-201","50":"B-303","51":"EB-201","53":"B-303","56":"EB-201","57":"B-303","58":"EB-201","60":"B-303"}}}},"CS 111":{"name":"Introduction to Computing in Engineering and Science","sections":{"1":{"instructor":"Özlem Özgü","schedule":{"8":"EB-201","10":"EB-201","15":"EB-201","17":"EB-201","22":"EB-201","24":"EB-201"}}}},"CS 112":{"name":"Introduction to Object-Oriented Programming","sections":{"1":{"instructor":"Abdullah Uz Tansel","schedule":{"36":"N/A","39":"N/A","42":"EB-202","43":"N/A","44":"EB-202","46":"N/A","49":"EB-202","50":"N/A","51":"EB-202","53":"N/A","56":"EB-202","57":"N/A","58":"EB-202","60":"N/A"}}}},"CS 121":{"name":"Introduction to Computing for Social Sciences","sections":{"1":{"instructor":"İsmail İpek","schedule":{"1":"N/A","2":"N/A","3":"N/A","8":"N/A","9":"N/A","10":"N/A","23":"N/A","24":"N/A","30":"N/A","31":"N/A"}}}},"CS 122":{"name":"Introduction to Programming for Social Sciences","sections":{"1":{"instructor":"Turgay Saracoğlu","schedule":{"7":"EB-102","8":"EB-102","14":"EB-102","15":"EB-102","21":"EB-102","22":"EB-102","35":"N/A","36":"N/A","42":"N/A","43":"N/A"}}}},"CS 202":{"name":"Fundamental Structures of Computer Science II","sections":{"1":{"instructor":"Markus Schaal","schedule":{"4":"EB-201","11":"EB-201","43":"EB-201","50":"EB-201","52":"EB-201","59":"EB-201"}}}},"CS 299":{"name":"Summer Training I","sections":{"1":{"instructor":"Staff","schedule":{}}}},"CS 399":{"name":"Summer Training II","sections":{"1":{"instructor":"Staff","schedule":{}}}}},"CTIS":{"CTIS 152":{"name":"Algorithms and Data Structures","sections":{"1":{"instructor":"Erkan Uçar","schedule":{"8":"N/A","9":"N/A","10":"N/A","15":"N/A","16":"N/A","17":"N/A","22":"N/A","23":"N/A","24":"N/A","29":"N/A","30":"N/A","31":"N/A","35":"N/A","42":"N/A","49":"N/A","56":"N/A"}},"2":{"instructor":"Serkan Genç","schedule":{"8":"N/A","9":"N/A","10":"N/A","15":"N/A","16":"N/A","17":"N/A","22":"N/A","23":"N/A","24":"N/A","29":"N/A","30":"N/A","31":"N/A","35":"N/A","42":"N/A","49":"N/A","56":"N/A"}}}},"CTIS 154":{"name":"Discrete Mathematics II","sections":{"1":{"instructor":"Duygu Albayrak","schedule":{"4":"N/A","11":"N/A","14":"N/A","21":"N/A","37":"N/A","44":"N/A"}}}},"CTIS 156":{"name":"Information Technologies II","sections":{"1":{"instructor":"Faruk Göloğlu","schedule":{"0":"N/A","7":"N/A","18":"N/A","25":"N/A","36":"N/A","43":"N/A"}}}}},"ECON":{"ECON 101":{"name":"Introduction to Economics I","sections":{"1":{"instructor":"Okan Üçer","schedule":{"0":"T-173","2":"T-173","3":"T-173","7":"T-173","9":"T-173","10":"T-173"}}}},"ECON 102":{"name":"Introduction to Economics II","sections":{"1":{"instructor":"Mehmet Polat","schedule":{"16":"T-173","17":"T-173","18":"T-173","23":"T-173","24":"T-173","25":"T-173"}}}},"ECON 103":{"name":"Principles of Economics","sections":{"1":{"instructor":"Recep Yüksel Altuğ","schedule":{"8":"B-Z06","9":"B-Z06","10":"B-Z06","15":"B-Z06","16":"B-Z06","17":"B-Z06"}}}},"ECON 201":{"name":"Economic Theory I","sections":{"1":{"instructor":"Staff","schedule":{"7":"A-125","9":"A-125","14":"A-125","16":"A-125","21":"A-125","23":"A-125"}}}},"ECON 202":{"name":"Economic Theory II","sections":{"1":{"instructor":"Esin Celasun","schedule":{"35":"A-125","37":"A-125","42":"A-125","44":"A-125","49":"A-125","51":"A-125"}}}},"ECON 221":{"name":"Introduction to Probability and Statistics I","sections":{"1":{"instructor":"Staff","schedule":{"8":"A-125","10":"A-125","15":"A-125","17":"A-125","22":"A-125","24":"A-125"}}}},"ECON 222":{"name":"Introduction to Probability and Statistics II","sections":{"1":{"instructor":"Syed Fahri Mahmud","schedule":{"36":"A-125","38":"A-125","43":"A-125","45":"A-125","50":"A-125","52":"A-125"}}}},"ECON 407":{"name":"Economics of Crises","sections":{"1":{"instructor":"Neil Lewis Arnwine","schedule":{"35":"B-Z07","37":"B-Z07","42":"B-Z07","44":"B-Z07","49":"B-Z07","51":"B-Z07"}}}}},"EEE":{"EEE 212":{"name":"Microprocessors","sections":{"1":{"instructor":"Ali Ziya Alkar","schedule":{"21":"EB-201","23":"EB-201","25":"EB-201","28":"EB-201","30":"EB-201","32":"EB-201","36":"N/A","43":"N/A","50":"N/A","57":"N/A"}}}},"EEE 391":{"name":"Basics of Signals and Systems","sections":{"1":{"instructor":"Orhan Arıkan","schedule":{"8":"EB-202","10":"EB-202","15":"EB-202","17":"EB-202","22":"EB-202","24":"EB-202"}}}},"EEE 399":{"name":"Summer Training II","sections":{"1":{"instructor":"Staff","schedule":{}}}},"EEE 491":{"name":"Senior Project I","sections":{"1":{"instructor":"Staff","schedule":{}}}},"EEE 603":{"name":"Advanced Electromagnetic Theory I","sections":{"1":{"instructor":"Ayhan Altıntaş","schedule":{"8":"EA-222","10":"EA-222","15":"EA-222","17":"EA-222","22":"EA-222","24":"EA-222"}}}}},"ELIT":{"ELIT 356":{"name":"Major Writers of the Neoclassical Period","sections":{"1":{"instructor":"M. Hamit Çalışkan","schedule":{"1":"H-334","8":"H-334","15":"H-334","45":"H-334","52":"H-334","59":"H-334"}}}},"ELIT 441":{"name":"British Drama I (from the Restoration to the 1950s)","sections":{"1":{"instructor":"M. Hamit Çalışkan","schedule":{"0":"H-335","3":"H-335","7":"H-335","10":"H-335","14":"H-335","17":"H-335"}}}},"ELIT 471":{"name":"Romantic Poetry","sections":{"1":{"instructor":"Sema Taşkın","schedule":{"35":"H-335","36":"H-335","42":"H-335","43":"H-335","49":"H-335","50":"H-335"}}}},"ELIT 474":{"name":"20th Century Poetry","sections":{"1":{"instructor":"Sema Taşkın","schedule":{"38":"H-335","39":"H-335","45":"H-335","46":"H-335","52":"H-335","53":"H-335"}}}}},"ENG":{"ENG 101":{"name":"English and Composition I","sections":{"3":{"instructor":"Şenol Bezci","schedule":{"14":"G-Z07","15":"G-Z07","16":"G-Z07","17":"G-Z07","18":"G-Z07","21":"G-Z07","22":"G-Z07","23":"G-Z07","24":"G-Z07","25":"G-Z07"}}}},"ENG 102":{"name":"English and Composition II","sections":{"1":{"instructor":"James Thurman","schedule":{"7":"G-210","8":"G-210","9":"G-210","10":"G-210","11":"G-210","14":"G-210","15":"G-210","16":"G-210","17":"G-210","18":"G-210"}},"2":{"instructor":"Çiğdem Selim-Dabir","schedule":{"21":"N/A","22":"N/A","23":"N/A","24":"N/A","25":"N/A","28":"N/A","29":"N/A","30":"N/A","31":"N/A","32":"N/A"}},"3":{"instructor":"Peter Paul Stephan","schedule":{"28":"G-132","29":"G-132","30":"G-132","31":"G-132","32":"G-132","35":"G-132","36":"G-132","37":"G-132","38":"G-132","39":"G-132"}},"4":{"instructor":"Ersin Soylu","schedule":{"7":"G-207","8":"G-207","9":"G-207","10":"G-207","11":"G-207","14":"G-207","15":"G-207","16":"G-207","17":"G-207","18":"G-207"}},"5":{"instructor":"Emel Bekişoğlu","schedule":{"21":"G-231","22":"G-231","23":"G-231","24":"G-231","25":"G-231","28":"G-231","29":"G-231","30":"G-231","31":"G-231","32":"G-231"}},"6":{"instructor":"Zeynep Özek","schedule":{"28":"G-210","29":"G-210","30":"G-210","31":"G-210","32":"G-210","35":"G-210","36":"G-210","37":"G-210","38":"G-210","39":"G-210"}},"7":{"instructor":"Ayşe Akçam Hendry","schedule":{"7":"G-107","8":"G-107","9":"G-107","10":"G-107","11":"G-107","14":"G-107","15":"G-107","16":"G-107","17":"G-107","18":"G-107"}},"8":{"instructor":"Mehmet Demirkaya","schedule":{"21":"B-Z05","22":"B-Z05","23":"B-Z05","24":"B-Z05","25":"B-Z05","28":"B-Z05","29":"B-Z05","30":"B-Z05","31":"B-Z05","32":"B-Z05"}},"9":{"instructor":"Bengisu Tanrıverdi Akalın","schedule":{"28":"G-Z10","29":"G-Z10","30":"G-Z10","31":"G-Z10","32":"G-Z10","35":"G-Z10","36":"G-Z10","37":"G-Z10","38":"G-Z10","39":"G-Z10"}}}},"ENG 241":{"name":"Sophomore Academic English I","sections":{"1":{"instructor":"Aynur Kadıoğlu","schedule":{"35":"G-231","37":"G-231","42":"G-231","44":"G-231","49":"G-231","51":"G-231"}},"2":{"instructor":"İklil Kaya Yıldırım","schedule":{"35":"G-207","37":"G-207","42":"G-207","44":"G-207","49":"G-207","51":"G-207"}}}}},"ETE":{"ETE 501":{"name":"Development of Instructional Materials","sections":{"1":{"instructor":"Necmi Akşit","schedule":{}}}}},"FA":{"FA 102":{"name":"Basic Design II","sections":{"1":{"instructor":"Sibel Ertez Ural","schedule":{"8":"FF-107","10":"FF-107","15":"FF-107","17":"FF-107","22":"FF-107","24":"FF-107","36":"FF-107","38":"FF-107","43":"FF-107","45":"FF-107","50":"FF-107","52":"FF-107","57":"FF-107","59":"FF-107"}},"2":{"instructor":"Semiha Yılmazer","schedule":{"8":"FF-109","10":"FF-109","15":"FF-109","17":"FF-109","22":"FF-109","24":"FF-109","36":"FF-109","38":"FF-109","43":"FF-109","45":"FF-109","50":"FF-109","52":"FF-109","57":"FF-109","59":"FF-109"}},"3":{"instructor":"Elif Mihçioğlu Bilgi","schedule":{"8":"FA-220","10":"FA-220","15":"FA-220","17":"FA-220","22":"FA-220","24":"FA-220","36":"FA-220","38":"FA-220","43":"FA-220","45":"FA-220","50":"FA-220","52":"FA-220","57":"FA-220","59":"FA-220"}}}},"FA 103":{"name":"Drawing I","sections":{"1":{"instructor":"Nina Kertselli","schedule":{"7":"FC-223","14":"FC-223","21":"FC-223","35":"FC-223","42":"FC-223","49":"FC-223"}}}},"FA 132":{"name":"Technical Drawing and Lettering II","sections":{"1":{"instructor":"Sezin Tanrıöver","schedule":{"37":"FF-107","39":"FF-107","44":"FF-107","46":"FF-107","51":"FF-107","53":"FF-107","58":"FF-107","60":"FF-107"}},"2":{"instructor":"Osman Demirbaş","schedule":{"37":"FF-109","39":"FF-109","44":"FF-109","46":"FF-109","51":"FF-109","53":"FF-109","58":"FF-109","60":"FF-109"}}}},"FA 171":{"name":"Introduction to Art and Culture I","sections":{"1":{"instructor":"Saadet Ayşe Gül Tokol","schedule":{"9":"FA-118","11":"FA-118","16":"FA-118","18":"FA-118","23":"FA-118","25":"FA-118"}}}},"FA 211":{"name":"Introduction to Painting I","sections":{"1":{"instructor":"Ilgım Veryeri Alaca","schedule":{"9":"FC-223","16":"FC-223","23":"FC-223","37":"FC-223","44":"FC-223","51":"FC-223"}}}},"FA 213":{"name":"Introduction to Printmaking I","sections":{"1":{"instructor":"Alexander Djikia","schedule":{"10":"FC-117","17":"FC-117","24":"FC-117","38":"FC-117","45":"FC-117","52":"FC-117"}}}},"FA 215":{"name":"Introduction to Sculpture I","sections":{"1":{"instructor":"Ercan Sağlam","schedule":{"9":"FC-123","16":"FC-123","23":"FC-123","37":"FC-123","44":"FC-123","51":"FC-123"}}}},"FA 217":{"name":"Introduction to Ceramics I","sections":{"1":{"instructor":"Ahmet Özsalar","schedule":{"7":"FE-101","14":"FE-101","21":"FE-101","35":"FE-101","42":"FE-101","49":"FE-101"}}}}},"HCIV":{"HCIV 101":{"name":"History of Civilization I","sections":{"1":{"instructor":"David E. Thornton","schedule":{"37":"B-Z06","39":"B-Z06","44":"B-Z06","46":"B-Z06","51":"B-Z06","53":"B-Z06"}}}},"HCIV 102":{"name":"History of Civilization II","sections":{"1":{"instructor":"David E. Thornton","schedule":{"35":"B-Z06","38":"B-Z06","42":"B-Z06","45":"B-Z06","49":"B-Z06","52":"B-Z06"}}}}},"HUM":{"HUM 111":{"name":"Cultures Civilizations and Ideas I","sections":{"1":{"instructor":"Mustafa Nakeeb","schedule":{"16":"G-228","18":"G-228","23":"G-228","25":"G-228","30":"G-228","32":"G-228"}}}},"HUM 112":{"name":"Cultures Civilizations and Ideas II","sections":{"1":{"instructor":"Thomas Kelso","schedule":{"36":"G-228","38":"G-228","43":"G-228","45":"G-228","50":"G-228","52":"G-228"}}}}},"IAED":{"IAED 202":{"name":"Interior Design Studio II","sections":{"1":{"instructor":"Alper Küçük  Veli Şafak Uysal","schedule":{"9":"FF-305","11":"FF-305","16":"FF-305","18":"FF-305","23":"FF-305","25":"FF-305","35":"FF-305","37":"FF-305","39":"FF-305","42":"FF-305","44":"FF-305","46":"FF-305","49":"FF-305","51":"FF-305","53":"FF-305","56":"FF-305","58":"FF-305","60":"FF-305"}}}},"IAED 251":{"name":"Construction and Materials I","sections":{"1":{"instructor":"Şule Taşlı Pektaş","schedule":{"1":"FF-213","3":"FF-213","8":"FF-213","10":"FF-213","15":"FF-213","17":"FF-213","22":"FF-213","24":"FF-213"}}}},"IAED 290":{"name":"Summer Practice I","sections":{"1":{"instructor":"Halime Demirkan","schedule":{}}}},"IAED 302":{"name":"Interior Design Studio IV","sections":{"1":{"instructor":"Necmiye Şule Aybar","schedule":{"9":"FF-105","11":"FF-105","16":"FF-105","18":"FF-105","23":"FF-105","25":"FF-105","35":"FF-105","37":"FF-105","39":"FF-105","42":"FF-105","44":"FF-105","46":"FF-105","49":"FF-105","51":"FF-105","53":"FF-105","56":"FF-105","58":"FF-105","60":"FF-105"}},"2":{"instructor":"Herbert Bassler","schedule":{"9":"FF-105","11":"FF-105","16":"FF-105","18":"FF-105","23":"FF-105","25":"FF-105","35":"FF-105","37":"FF-105","39":"FF-105","42":"FF-105","44":"FF-105","46":"FF-105","49":"FF-105","51":"FF-105","53":"FF-105","56":"FF-105","58":"FF-105","60":"FF-105"}}}},"IAED 341":{"name":"Building Performance: Codes","sections":{"1":{"instructor":"Cengiz Yener","schedule":{"36":"FF-202","38":"FF-202","43":"FF-202","45":"FF-202","50":"FF-202","52":"FF-202"}}}},"IAED 351":{"name":"Detailing Studio","sections":{"1":{"instructor":"Osman Demirbaş","schedule":{"8":"FF-105","10":"FF-105","15":"FF-105","17":"FF-105","22":"FF-105","24":"FF-105"}},"2":{"instructor":"Tomris Yardımcı","schedule":{"8":"FF-106","10":"FF-106","15":"FF-106","17":"FF-106","22":"FF-106","24":"FF-106"}}}},"IAED 390":{"name":"Summer Practice II","sections":{"1":{"instructor":"Halime Demirkan","schedule":{}}}},"IAED 415":{"name":"Modular Interior Systems","sections":{"1":{"instructor":"Serpil Altay","schedule":{"8":"FF-310","10":"FF-310","15":"FF-310","17":"FF-310","22":"FF-310","24":"FF-310"}}}},"IAED 417":{"name":"Interior Design Documentation","sections":{"1":{"instructor":"Serpil Altay","schedule":{"36":"FF-310","38":"FF-310","43":"FF-310","45":"FF-310","50":"FF-310","52":"FF-310"}}}}},"IE":{"IE 325":{"name":"Stochastic Models","sections":{"1":{"instructor":"Mehmet Murat Fadıloğlu","schedule":{"8":"EB-203","11":"EB-203","15":"EB-203","18":"EB-203","22":"EB-203","25":"EB-203"}}}},"IE 563":{"name":"Game Theory With Applications in Operations Management","sections":{"1":{"instructor":"Staff","schedule":{"43":"EA-302","45":"EA-302","50":"EA-302","52":"EA-302","57":"EA-302","59":"EA-302"}}}},"IE 699":{"name":"Ph.D. Dissertation","sections":{"1":{"instructor":"Staff","schedule":{}}}}},"IR":{"IR 203":{"name":"International Relations I","sections":{"1":{"instructor":"Ayşe Gülgün Tuna","schedule":{"14":"T-272","15":"T-272","21":"T-272","22":"T-272","28":"T-272","29":"T-272"}}}},"IR 204":{"name":"International Relations II","sections":{"1":{"instructor":"Ayşe Gülgün Tuna","schedule":{"35":"T-272","36":"T-272","42":"T-272","43":"T-272","49":"T-272","50":"T-272"}}}},"IR 205":{"name":"Diplomatic History I","sections":{"1":{"instructor":"Sergei Podbolotov","schedule":{"7":"A-331","10":"A-331","14":"A-331","17":"A-331","21":"A-331","24":"A-331"}}}},"IR 229":{"name":"Research Methods I","sections":{"1":{"instructor":"Wlodzimierz Korab-Karpowicz","schedule":{"7":"B-Z07","9":"B-Z07","14":"B-Z07","16":"B-Z07","21":"B-Z07","23":"B-Z07"}}}},"IR 230":{"name":"Research Methods II","sections":{"1":{"instructor":"Wlodzimierz Korab-Karpowicz","schedule":{"8":"B-Z07","10":"B-Z07","15":"B-Z07","17":"B-Z07","22":"B-Z07","24":"B-Z07"}}}},"IR 305":{"name":"International Organizations","sections":{"1":{"instructor":"Pınar İpek","schedule":{"14":"T-173","15":"T-173","21":"T-173","22":"T-173","28":"T-173","29":"T-173"}}}},"IR 318":{"name":"Contemporary Balkan Politics","sections":{"1":{"instructor":"Hasan Ünal","schedule":{"9":"A-330","10":"A-330","16":"A-330","17":"A-330","23":"A-330","24":"A-330"}}}},"IR 335":{"name":"International Relations Theory","sections":{"1":{"instructor":"Ali Tekin","schedule":{"36":"A-230","38":"A-230","43":"A-230","45":"A-230","50":"A-230","52":"A-230"}}}},"IR 338":{"name":"Politics of International Economy","sections":{"1":{"instructor":"Tore Fougner","schedule":{"8":"A-331","9":"A-331","15":"A-331","16":"A-331","22":"A-331","23":"A-331"}}}},"IR 439":{"name":"Turkish Foreign Policy ","sections":{"1":{"instructor":"Nur Bilge Criss","schedule":{"7":"T-172","9":"T-172","14":"T-172","16":"T-172","21":"T-172","23":"T-172"}}}}},"LAUD":{"LAUD 190":{"name":"Summer Practice I","sections":{"1":{"instructor":"Staff","schedule":{}}}}},"LAW":{"LAW 101":{"name":"Introduction to Law","sections":{"1":{"instructor":"Gülriz Uygur","schedule":{"7":"B-113","11":"B-113","14":"B-113","18":"B-113","21":"B-113","25":"B-113"}}}},"LAW 102":{"name":"Roman Law","sections":{"1":{"instructor":"Haluk Emiroğlu","schedule":{"9":"B-113","10":"B-113","16":"B-113","17":"B-113","23":"B-113","24":"B-113"}}}},"LAW 103":{"name":"Constitutional Law I","sections":{"1":{"instructor":"Erdal Onar","schedule":{"36":"B-113","37":"B-113","43":"B-113","44":"B-113","50":"B-113","51":"B-113"}}}}},"MAN":{"MAN 211":{"name":"Principles of Accounting I","sections":{"1":{"instructor":"Hamdi Aydın","schedule":{"10":"B-114","17":"B-114","24":"B-114","36":"B-114","43":"B-114","50":"B-114"}}}},"MAN 321":{"name":"Corporate Finance","sections":{"1":{"instructor":"Aslıhan Salih","schedule":{"36":"MA-301","38":"MA-301","43":"MA-301","45":"MA-301","50":"MA-301","52":"MA-301"}}}},"MAN 335":{"name":"Fundamentals of Marketing","sections":{"1":{"instructor":"Ahmet Ekici","schedule":{"7":"MA-301","9":"MA-301","14":"MA-301","16":"MA-301","21":"MA-301","23":"MA-301"}}}},"MAN 401":{"name":"Managerial Economics","sections":{"1":{"instructor":"Levent Akdeniz","schedule":{"8":"MA-301","10":"MA-301","15":"MA-301","17":"MA-301","22":"MA-301","24":"MA-301"}}}},"MAN 540":{"name":"Special Topics in Quantitative Methods","sections":{"1":{"instructor":"Staff","schedule":{}}}},"MAN 599":{"name":"Master's Thesis Project","sections":{"1":{"instructor":"Staff","schedule":{}}}},"MAN 639":{"name":"Special Topics in Marketing","sections":{"1":{"instructor":"Staff","schedule":{}}}}},"MATH":{"MATH 102":{"name":"Calculus II","sections":{"1":{"instructor":"Uğur Madran","schedule":{"7":"B-Z02","9":"B-Z02","11":"B-Z02","14":"B-Z02","16":"B-Z02","18":"B-Z02","21":"B-Z02","23":"B-Z02","25":"B-Z02"}}}},"MATH 106":{"name":"Introduction to Calculus II","sections":{"1":{"instructor":"Ümit Özger","schedule":{"35":"B-112","36":"B-112","38":"B-112","42":"B-112","43":"B-112","45":"B-112","49":"B-112","50":"B-112","52":"B-112"}}}},"MATH 112":{"name":"Intermediate Calculus II","sections":{"1":{"instructor":"Yosum Kurtulmaz","schedule":{"0":"B-Z01","2":"B-Z01","4":"B-Z01","7":"B-Z01","9":"B-Z01","11":"B-Z01","14":"B-Z01","16":"B-Z01","18":"B-Z01"}}}},"MATH 116":{"name":"Intermediate Calculus III","sections":{"1":{"instructor":"Alexandre Goncharov","schedule":{"0":"N/A","2":"N/A","4":"N/A","7":"N/A","9":"N/A","11":"N/A","14":"N/A","16":"N/A","18":"N/A"}},"2":{"instructor":"Alexandre Goncharov","schedule":{"35":"N/A","37":"N/A","39":"N/A","42":"N/A","44":"N/A","46":"N/A","49":"N/A","51":"N/A","53":"N/A"}},"3":{"instructor":"Aydan Pamir","schedule":{"0":"B-Z05","2":"B-Z05","4":"B-Z05","7":"B-Z05","9":"B-Z05","11":"B-Z05","14":"B-Z05","16":"B-Z05","18":"B-Z05"}},"4":{"instructor":"Aydan Pamir","schedule":{"35":"B-Z05","37":"B-Z05","39":"B-Z05","42":"B-Z05","44":"B-Z05","46":"B-Z05","49":"B-Z05","51":"B-Z05","53":"B-Z05"}},"5":{"instructor":"Natalia Zheltukhina","schedule":{"0":"SA-Z18","2":"SA-Z18","4":"SA-Z18","7":"SA-Z18","9":"SA-Z18","11":"SA-Z18","14":"SA-Z18","16":"SA-Z18","18":"SA-Z18"}}}},"MATH 215":{"name":"Mathematical Analysis","sections":{"1":{"instructor":"Mefharet Kocatepe","schedule":{"7":"B-Z04","8":"B-Z04","10":"B-Z04","14":"B-Z04","15":"B-Z04","17":"B-Z04","24":"B-Z04"}}}},"MATH 225":{"name":"Linear Algebra and Differential Equations","sections":{"1":{"instructor":"Uğurhan Muğan","schedule":{"0":"B-Z08","2":"B-Z08","3":"B-Z08","7":"B-Z08","9":"B-Z08","10":"B-Z08","14":"B-Z08","16":"B-Z08","17":"B-Z08"}}}},"MATH 250":{"name":"Introduction to Probability","sections":{"1":{"instructor":"Dilek Köksal","schedule":{"35":"B-Z02","37":"B-Z02","38":"B-Z02","42":"B-Z02","44":"B-Z02","45":"B-Z02","51":"B-Z02"}}}},"MATH 260":{"name":"Introduction to Statistics","sections":{"1":{"instructor":"Ayten Türkcan","schedule":{"57":"EA-502","58":"EA-502","59":"EA-502","64":"EA-502","65":"EA-502","66":"EA-502"}}}},"MATH 291":{"name":"Summer Project I","sections":{"1":{"instructor":"Alexandre Klyachko","schedule":{}},"2":{"instructor":"Ergün Yalçın","schedule":{}},"3":{"instructor":"Azer Kerimov","schedule":{}}}},"MATH 391":{"name":"Summer Project II","sections":{"1":{"instructor":"Alexandre Goncharov","schedule":{}}}},"MATH 491":{"name":"Senior Project I","sections":{"1":{"instructor":"Azer Kerimov","schedule":{}}}}},"PHIL":{"PHIL 241":{"name":"Social and Political Philosophy I","sections":{"1":{"instructor":"Geoffrey Scott Bowe","schedule":{"36":"FA-120","38":"FA-120","43":"FA-120","45":"FA-120","50":"FA-120","52":"FA-120"}},"2":{"instructor":"Lucas Thorpe","schedule":{"36":"FA-121","38":"FA-121","43":"FA-121","45":"FA-121","50":"FA-121","52":"FA-121"}}}}},"PHYS":{"PHYS 102":{"name":"General Physics II","sections":{"1":{"instructor":"Bilal Tanatar","schedule":{"0":"SA-Z04","1":"SA-Z04","2":"SA-Z04","3":"SA-Z04","4":"SA-Z04","7":"SA-Z04","9":"SA-Z04","11":"SA-Z04"}}}}},"POLS":{"POLS 101":{"name":"Introduction to Political Science I","sections":{"1":{"instructor":"İhsan İlker Aytürk","schedule":{"7":"A-127","8":"A-127","14":"A-127","15":"A-127","21":"A-127","22":"A-127"}}}},"POLS 104":{"name":"Introduction to Political Science II","sections":{"1":{"instructor":"Ülkem Özge Sevgilier","schedule":{"35":"T-173","36":"T-173","42":"T-173","43":"T-173","49":"T-173","50":"T-173"}}}},"POLS 430":{"name":"Policy  Analysis","sections":{"1":{"instructor":"Ömer Faruk Gençkaya","schedule":{"50":"B-111","52":"B-111","57":"B-111","59":"B-111","64":"B-111","66":"B-111"}}}},"POLS 433":{"name":"Politics of European Integration","sections":{"1":{"instructor":"Aylin Güney","schedule":{"15":"A-Z27","16":"A-Z27","18":"A-Z27","22":"A-Z27","23":"A-Z27","25":"A-Z27"}}}},"POLS 453":{"name":"Comparative Legislatures","sections":{"1":{"instructor":"Ömer Faruk Gençkaya","schedule":{"10":"B-111","17":"B-111","24":"B-111","51":"B-111","58":"B-111","65":"B-111"}}}},"POLS 455":{"name":"World Politics I","sections":{"1":{"instructor":"Aylin Güney","schedule":{"36":"A-Z27","37":"A-Z27","39":"A-Z27","43":"A-Z27","44":"A-Z27","46":"A-Z27"}}}},"POLS 476":{"name":"World Politics II","sections":{"1":{"instructor":"Lerna Yanık","schedule":{"8":"A-230","9":"A-230","15":"A-230","16":"A-230","22":"A-230","23":"A-230"}}}}},"PSYC":{"PSYC 102":{"name":"Introduction to Social Psychology","sections":{"1":{"instructor":"Süheyla Pinar","schedule":{"14":"A-231","16":"A-231","21":"A-231","23":"A-231","28":"A-231","30":"A-231"}}}}},"SOC":{"SOC 101":{"name":"Introduction to Sociology","sections":{"1":{"instructor":"Süheyla Pinar","schedule":{"1":"A-231","3":"A-231","8":"A-231","10":"A-231","15":"A-231","17":"A-231"}}}}},"TE":{"TE 504":{"name":"Educational Technology and Materials Development","sections":{"1":{"instructor":"Mesut Duran","schedule":{}}}},"TE 505":{"name":"Guidance","sections":{"1":{"instructor":"Paul Nelson","schedule":{}}}}},"TEFL":{"TEFL 553":{"name":"Research Seminar III","sections":{"1":{"instructor":"Ted Rodgers","schedule":{}}}},"TEFL 554":{"name":"Thesis Writing","sections":{"1":{"instructor":"Susan S. Johnston","schedule":{}}}}},"THM":{"THM 164":{"name":"Calculus","sections":{"1":{"instructor":"Kamer Rodoplu","schedule":{"8":"RE-203","15":"RE-203","22":"RE-203","38":"RE-203","45":"RE-203","52":"RE-203"}}}},"THM 245":{"name":"Purchasing and Cost Analysis","sections":{"1":{"instructor":"Esin Şenol","schedule":{"8":"RB-103","15":"RB-103","22":"RB-103","37":"RB-103","44":"RB-103","51":"RB-103"}}}},"THM 269":{"name":"Co-Op Management Application","sections":{"1":{"instructor":"Engin Türel","schedule":{}}}},"THM 409":{"name":"Tourism Law","sections":{"1":{"instructor":"Cem Tarhan","schedule":{"10":"RB-102","17":"RB-102","24":"RB-102","37":"RB-102","44":"RB-102","51":"RB-102"}}}},"THM 415":{"name":"Finance","sections":{"1":{"instructor":"Cevat Ertuna","schedule":{"8":"RE-001","15":"RE-001","22":"RE-001","38":"RE-001","45":"RE-001","52":"RE-001"}}}},"THM 417":{"name":"Quantitative Decision Techniques","sections":{"1":{"instructor":"Cevat Ertuna","schedule":{"9":"RE-001","16":"RE-001","23":"RE-001","39":"RE-001","46":"RE-001","53":"RE-001"}}}},"THM 419":{"name":"Tourism Management Applications","sections":{"1":{"instructor":"M.Teoman Alemdar","schedule":{"10":"RB-201","17":"RB-201","24":"RB-201","35":"RB-201","42":"RB-201","49":"RB-201"}}}},"THM 423":{"name":"Tourism Economics","sections":{"1":{"instructor":"Cem Tarhan","schedule":{"11":"RB-102","18":"RB-102","25":"RB-102","36":"RB-102","43":"RB-102","50":"RB-102"}}}}},"TRIN":{"TRIN 102":{"name":"Applied Linguistics","sections":{"1":{"instructor":"Abdulhak Hamit Sunel","schedule":{"1":"LB-102","3":"LB-102","8":"LB-102","10":"LB-102","15":"LB-102","17":"LB-102"}}}}}}